{
  "topic_representations": {
    "-1": [
      [
        "und",
        0.012885069068544544
      ],
      [
        "der",
        0.012869091398406161
      ],
      [
        "die",
        0.01283856241566456
      ],
      [
        "in",
        0.011354959136510181
      ],
      [
        "zu",
        0.010395795508905854
      ],
      [
        "den",
        0.010065661118298427
      ],
      [
        "von",
        0.00975948869298434
      ],
      [
        "das",
        0.009534480292917166
      ],
      [
        "des",
        0.009039979637493737
      ],
      [
        "sie",
        0.009009478379916216
      ]
    ],
    "0": [
      [
        "vnd",
        0.019954240571452203
      ],
      [
        "da",
        0.011813633361092184
      ],
      [
        "und",
        0.011334062521737088
      ],
      [
        "der",
        0.01081273516583197
      ],
      [
        "er",
        0.010557146296970304
      ],
      [
        "die",
        0.01040001269927659
      ],
      [
        "zu",
        0.01020840265400738
      ],
      [
        "nicht",
        0.010170581091567975
      ],
      [
        "das",
        0.009944614247928687
      ],
      [
        "in",
        0.00991408765378247
      ]
    ],
    "1": [
      [
        "die",
        0.014127889533562192
      ],
      [
        "sie",
        0.013301404831090676
      ],
      [
        "und",
        0.013186189949455288
      ],
      [
        "der",
        0.012826783349602213
      ],
      [
        "ich",
        0.012462600072847982
      ],
      [
        "zu",
        0.01181014784992911
      ],
      [
        "nicht",
        0.011299146774778453
      ],
      [
        "das",
        0.011196144349448857
      ],
      [
        "ist",
        0.010911633350403514
      ],
      [
        "sprache",
        0.010577101079346563
      ]
    ],
    "2": [
      [
        "die",
        0.017132847268132606
      ],
      [
        "der",
        0.01634348651624706
      ],
      [
        "und",
        0.012223714050615732
      ],
      [
        "zu",
        0.01196898157932548
      ],
      [
        "den",
        0.011937220399832523
      ],
      [
        "des",
        0.011814326107897111
      ],
      [
        "in",
        0.011272182347761861
      ],
      [
        "von",
        0.010199628799934472
      ],
      [
        "das",
        0.010069156100538842
      ],
      [
        "fuer",
        0.009756722115815379
      ]
    ],
    "3": [
      [
        "und",
        0.015258471426690557
      ],
      [
        "ein",
        0.011762266748881655
      ],
      [
        "sie",
        0.011358341368885904
      ],
      [
        "es",
        0.011078082184996082
      ],
      [
        "mit",
        0.011032477514136734
      ],
      [
        "in",
        0.010798189652306086
      ],
      [
        "die",
        0.010796722123205753
      ],
      [
        "so",
        0.01064306160256968
      ],
      [
        "da",
        0.010137665381589578
      ],
      [
        "den",
        0.010048974301781565
      ]
    ],
    "4": [
      [
        "der",
        0.015959436686425542
      ],
      [
        "die",
        0.015390053526478115
      ],
      [
        "des",
        0.013130984354776446
      ],
      [
        "und",
        0.013041099204041158
      ],
      [
        "in",
        0.012874633703356205
      ],
      [
        "von",
        0.012749424787187588
      ],
      [
        "zu",
        0.012249890751308282
      ],
      [
        "den",
        0.01161161791214
      ],
      [
        "auf",
        0.009329645734149126
      ],
      [
        "sich",
        0.00921612034968691
      ]
    ],
    "5": [
      [
        "ich",
        0.015254455393536197
      ],
      [
        "er",
        0.014504441924211652
      ],
      [
        "und",
        0.014466832167344608
      ],
      [
        "sie",
        0.01385427979718458
      ],
      [
        "war",
        0.01168806541215298
      ],
      [
        "der",
        0.011674337511981167
      ],
      [
        "die",
        0.011343115488479423
      ],
      [
        "zu",
        0.010488508072256915
      ],
      [
        "in",
        0.010480241396813732
      ],
      [
        "das",
        0.01031664185616034
      ]
    ],
    "6": [
      [
        "die",
        0.01726551533091211
      ],
      [
        "der",
        0.016820472824375658
      ],
      [
        "des",
        0.012857202755088408
      ],
      [
        "den",
        0.012783237608811655
      ],
      [
        "und",
        0.012687928406478859
      ],
      [
        "zu",
        0.01244354294484243
      ],
      [
        "in",
        0.011637883464572216
      ],
      [
        "von",
        0.011027086667860495
      ],
      [
        "dem",
        0.009641501621608753
      ],
      [
        "auf",
        0.009531351112166374
      ]
    ],
    "7": [
      [
        "und",
        0.014429872619810253
      ],
      [
        "die",
        0.013132726998663144
      ],
      [
        "der",
        0.012758491113311699
      ],
      [
        "in",
        0.012649612956165122
      ],
      [
        "von",
        0.011752447856285406
      ],
      [
        "den",
        0.010925243965238697
      ],
      [
        "mit",
        0.009729405234036353
      ],
      [
        "das",
        0.009629552668213378
      ],
      [
        "des",
        0.00952944420032217
      ],
      [
        "zu",
        0.009383287330484191
      ]
    ],
    "8": [
      [
        "die",
        0.015901665909435914
      ],
      [
        "der",
        0.01568775923161416
      ],
      [
        "den",
        0.012246259004448838
      ],
      [
        "und",
        0.012178677367720388
      ],
      [
        "in",
        0.011940903407174833
      ],
      [
        "zu",
        0.011644370690605619
      ],
      [
        "des",
        0.010806635444904022
      ],
      [
        "von",
        0.01026149033178814
      ],
      [
        "april",
        0.010154803120220842
      ],
      [
        "fuer",
        0.00949502578839577
      ]
    ],
    "9": [
      [
        "und",
        0.014422101591808869
      ],
      [
        "die",
        0.013141863432606782
      ],
      [
        "der",
        0.012728322742471054
      ],
      [
        "in",
        0.011076720713801357
      ],
      [
        "ein",
        0.010712449998698874
      ],
      [
        "sie",
        0.010467125319844972
      ],
      [
        "mit",
        0.010020682002144716
      ],
      [
        "das",
        0.009997881000937113
      ],
      [
        "den",
        0.009831437313717864
      ],
      [
        "so",
        0.009750250085491524
      ]
    ],
    "10": [
      [
        "marburger",
        0.01830987560730123
      ],
      [
        "marburg",
        0.016197859773114356
      ],
      [
        "der",
        0.01565465085172424
      ],
      [
        "die",
        0.014820292154894867
      ],
      [
        "in",
        0.013337583492540883
      ],
      [
        "des",
        0.012138556833084544
      ],
      [
        "und",
        0.012064806166648312
      ],
      [
        "den",
        0.011307448295211728
      ],
      [
        "wurde",
        0.011176719901445918
      ],
      [
        "im",
        0.01061299863427349
      ]
    ],
    "11": [
      [
        "die",
        0.016022292452274
      ],
      [
        "der",
        0.01550574320363672
      ],
      [
        "und",
        0.012537745888603177
      ],
      [
        "des",
        0.012240235474850713
      ],
      [
        "zu",
        0.011826634103525552
      ],
      [
        "in",
        0.011467922210005182
      ],
      [
        "den",
        0.011261810943053896
      ],
      [
        "von",
        0.010093519922249388
      ],
      [
        "da",
        0.009626223367793648
      ],
      [
        "das",
        0.00928235845272495
      ]
    ],
    "12": [
      [
        "die",
        0.015573070914235683
      ],
      [
        "der",
        0.015284692946220889
      ],
      [
        "und",
        0.013991425658090405
      ],
      [
        "den",
        0.012297666796042791
      ],
      [
        "in",
        0.011681113995239535
      ],
      [
        "ist",
        0.011547924725382621
      ],
      [
        "des",
        0.011483967611411162
      ],
      [
        "sind",
        0.01118419534874545
      ],
      [
        "von",
        0.010638652182577764
      ],
      [
        "oder",
        0.010231346749822842
      ]
    ],
    "13": [
      [
        "die",
        0.014846176938600594
      ],
      [
        "der",
        0.01456933506542754
      ],
      [
        "und",
        0.012914373367022822
      ],
      [
        "in",
        0.012648382802226384
      ],
      [
        "des",
        0.012084320666559841
      ],
      [
        "von",
        0.011322598130053462
      ],
      [
        "zu",
        0.011183761091755232
      ],
      [
        "den",
        0.010876761945583496
      ],
      [
        "das",
        0.009942108268446005
      ],
      [
        "dem",
        0.009597665456345456
      ]
    ],
    "14": [
      [
        "in",
        0.014564919206451237
      ],
      [
        "die",
        0.014067256825755827
      ],
      [
        "der",
        0.013826398575549095
      ],
      [
        "fuer",
        0.013774132160534882
      ],
      [
        "und",
        0.013648757759319605
      ],
      [
        "von",
        0.011736717748865125
      ],
      [
        "zu",
        0.010570640909823813
      ],
      [
        "den",
        0.0103283325811276
      ],
      [
        "des",
        0.00974401342383077
      ],
      [
        "eine",
        0.009527943645220617
      ]
    ],
    "15": [
      [
        "die",
        0.016736962136354668
      ],
      [
        "der",
        0.015371477818004667
      ],
      [
        "man",
        0.014887128025449147
      ],
      [
        "ist",
        0.014050442873614146
      ],
      [
        "in",
        0.012832154208072322
      ],
      [
        "so",
        0.012046780541161258
      ],
      [
        "von",
        0.01164565024718389
      ],
      [
        "eine",
        0.011132440232568841
      ],
      [
        "das",
        0.010917869894808504
      ],
      [
        "und",
        0.010785499640696845
      ]
    ],
    "16": [
      [
        "juli",
        0.017996190667991664
      ],
      [
        "der",
        0.01622843627408682
      ],
      [
        "die",
        0.01622780480565167
      ],
      [
        "und",
        0.012124840038965893
      ],
      [
        "des",
        0.012115492204147944
      ],
      [
        "in",
        0.011779920393516786
      ],
      [
        "zu",
        0.011645396538411595
      ],
      [
        "den",
        0.011597957591995889
      ],
      [
        "von",
        0.010389265266019188
      ],
      [
        "fuer",
        0.009478331745938005
      ]
    ],
    "17": [
      [
        "der",
        0.015021817458179251
      ],
      [
        "die",
        0.01454182376016493
      ],
      [
        "in",
        0.013211862306007929
      ],
      [
        "und",
        0.012174745898665759
      ],
      [
        "des",
        0.012067599240332688
      ],
      [
        "zu",
        0.011612639932973618
      ],
      [
        "den",
        0.010811729932221709
      ],
      [
        "von",
        0.009717564082464205
      ],
      [
        "ist",
        0.009324499598088258
      ],
      [
        "das",
        0.009105653715281783
      ]
    ],
    "18": [
      [
        "die",
        0.016973933413973907
      ],
      [
        "der",
        0.016517220197743446
      ],
      [
        "maerz",
        0.01521042201013149
      ],
      [
        "zu",
        0.012058773047690131
      ],
      [
        "den",
        0.011870817349083155
      ],
      [
        "und",
        0.011676303361305842
      ],
      [
        "in",
        0.011527171223868956
      ],
      [
        "des",
        0.011029898242784823
      ],
      [
        "das",
        0.010204287151961451
      ],
      [
        "von",
        0.010015697883881623
      ]
    ],
    "19": [
      [
        "die",
        0.013440002223346535
      ],
      [
        "vnd",
        0.012954333094689602
      ],
      [
        "der",
        0.012741870455829836
      ],
      [
        "in",
        0.01265097912714922
      ],
      [
        "den",
        0.010506167725798399
      ],
      [
        "zu",
        0.010356316820670319
      ],
      [
        "und",
        0.009659649205626088
      ],
      [
        "von",
        0.009385747777994582
      ],
      [
        "des",
        0.008833348280102892
      ],
      [
        "fuer",
        0.008663649670906963
      ]
    ],
    "20": [
      [
        "der",
        0.018884198663716167
      ],
      [
        "die",
        0.01638165382020358
      ],
      [
        "des",
        0.014632037585556522
      ],
      [
        "von",
        0.014302952845809831
      ],
      [
        "in",
        0.013287517524941431
      ],
      [
        "und",
        0.011669663754305263
      ],
      [
        "ist",
        0.011171111920407529
      ],
      [
        "erde",
        0.010866178196254395
      ],
      [
        "den",
        0.010499618195090966
      ],
      [
        "sonne",
        0.010265621145113235
      ]
    ],
    "21": [
      [
        "nationalversammlung",
        0.018296155000158226
      ],
      [
        "die",
        0.01684155436225144
      ],
      [
        "der",
        0.015738005014993516
      ],
      [
        "zu",
        0.012212332439836878
      ],
      [
        "und",
        0.012002721662400245
      ],
      [
        "den",
        0.01195019844368119
      ],
      [
        "des",
        0.011883643362207593
      ],
      [
        "in",
        0.011151128369145762
      ],
      [
        "von",
        0.010749430476515396
      ],
      [
        "november",
        0.010146967677074313
      ]
    ],
    "22": [
      [
        "von",
        0.019870025396944373
      ],
      [
        "und",
        0.013715292778397113
      ],
      [
        "der",
        0.013225093667629157
      ],
      [
        "den",
        0.012783478059835549
      ],
      [
        "zu",
        0.012680040586204637
      ],
      [
        "koenigl",
        0.011822515830637287
      ],
      [
        "nach",
        0.011589747281529866
      ],
      [
        "die",
        0.011357397088636315
      ],
      [
        "bey",
        0.011326816346774243
      ],
      [
        "in",
        0.010738588405262811
      ]
    ],
    "23": [
      [
        "der",
        0.015776158567657163
      ],
      [
        "die",
        0.015448763824041364
      ],
      [
        "in",
        0.013091244911884547
      ],
      [
        "des",
        0.013001972132559192
      ],
      [
        "und",
        0.012779017736822546
      ],
      [
        "zu",
        0.0123442452697568
      ],
      [
        "von",
        0.012224815565739143
      ],
      [
        "den",
        0.011187662555750788
      ],
      [
        "auf",
        0.009347589208636911
      ],
      [
        "da",
        0.009332915101501861
      ]
    ],
    "24": [
      [
        "und",
        0.01345477673026696
      ],
      [
        "der",
        0.013352944523342564
      ],
      [
        "die",
        0.013069048265939692
      ],
      [
        "er",
        0.01164256320246176
      ],
      [
        "zu",
        0.011259884189630002
      ],
      [
        "den",
        0.011186176231881721
      ],
      [
        "in",
        0.011030865156016157
      ],
      [
        "ich",
        0.010982749169530369
      ],
      [
        "sich",
        0.010298627889566845
      ],
      [
        "auf",
        0.010058257424482282
      ]
    ],
    "25": [
      [
        "von",
        0.017703935473498376
      ],
      [
        "der",
        0.013995188179375243
      ],
      [
        "und",
        0.013329837428695823
      ],
      [
        "den",
        0.013118785949851303
      ],
      [
        "zu",
        0.012687227220160633
      ],
      [
        "de",
        0.012563163849444024
      ],
      [
        "des",
        0.01219083676634448
      ],
      [
        "die",
        0.011845939578144454
      ],
      [
        "ten",
        0.011692262977043885
      ],
      [
        "dem",
        0.010583764212229837
      ]
    ],
    "26": [
      [
        "fl",
        0.023749238820536096
      ],
      [
        "der",
        0.01733260535552276
      ],
      [
        "die",
        0.01551834639277281
      ],
      [
        "wien",
        0.014512630441207349
      ],
      [
        "in",
        0.01373362721505883
      ],
      [
        "des",
        0.012862395921640587
      ],
      [
        "dto",
        0.012130119898894544
      ],
      [
        "und",
        0.011421567394738588
      ],
      [
        "den",
        0.011351815790623283
      ],
      [
        "dr",
        0.010923199347834877
      ]
    ],
    "27": [
      [
        "die",
        0.017635065791753446
      ],
      [
        "der",
        0.01501285897194271
      ],
      [
        "in",
        0.012811432538102373
      ],
      [
        "und",
        0.012616980135205253
      ],
      [
        "den",
        0.011761642122143246
      ],
      [
        "des",
        0.010590438279306905
      ],
      [
        "zu",
        0.010583871846530882
      ],
      [
        "von",
        0.010425966284536453
      ],
      [
        "sich",
        0.009948130713270022
      ],
      [
        "auf",
        0.00929023327035796
      ]
    ],
    "28": [
      [
        "czernowitz",
        0.021972657214489426
      ],
      [
        "cz",
        0.01843974230852887
      ],
      [
        "der",
        0.018147463959786288
      ],
      [
        "die",
        0.01634342802352853
      ],
      [
        "allg",
        0.016012916747914684
      ],
      [
        "dr",
        0.01594104814135977
      ],
      [
        "ztg",
        0.015898253810015
      ],
      [
        "in",
        0.013511277004097318
      ],
      [
        "des",
        0.01314763369231448
      ],
      [
        "czernowitzer",
        0.012502367654829236
      ]
    ],
    "29": [
      [
        "du",
        0.014692818447619499
      ],
      [
        "und",
        0.013517101022164257
      ],
      [
        "ich",
        0.013407329136818441
      ],
      [
        "die",
        0.01254775488587342
      ],
      [
        "ein",
        0.012505042384553591
      ],
      [
        "so",
        0.01200137854846817
      ],
      [
        "mein",
        0.011920295498678795
      ],
      [
        "der",
        0.011338095677717295
      ],
      [
        "dein",
        0.010970337620344196
      ],
      [
        "was",
        0.010834631343676092
      ]
    ],
    "30": [
      [
        "der",
        0.013972636205604927
      ],
      [
        "die",
        0.013760055088311938
      ],
      [
        "und",
        0.012908474419540484
      ],
      [
        "in",
        0.01149445946196043
      ],
      [
        "den",
        0.010988205812558894
      ],
      [
        "von",
        0.010914216496790573
      ],
      [
        "oder",
        0.010793104084049859
      ],
      [
        "obs",
        0.010741054048271035
      ],
      [
        "des",
        0.010365773755091227
      ],
      [
        "eine",
        0.010001925140116245
      ]
    ],
    "31": [
      [
        "der",
        0.018515450298190333
      ],
      [
        "des",
        0.015764024651842453
      ],
      [
        "die",
        0.01547036481315037
      ],
      [
        "von",
        0.015403766084361645
      ],
      [
        "in",
        0.014970026490869762
      ],
      [
        "akademie",
        0.013766895850618093
      ],
      [
        "und",
        0.013373663711612692
      ],
      [
        "den",
        0.01182642286400735
      ],
      [
        "curtius",
        0.011613768828641237
      ],
      [
        "ueber",
        0.011592448519522212
      ]
    ],
    "32": [
      [
        "die",
        0.01658791143515988
      ],
      [
        "juni",
        0.01611583119069837
      ],
      [
        "der",
        0.015754536981234708
      ],
      [
        "zu",
        0.01223518042402671
      ],
      [
        "und",
        0.01220988949953184
      ],
      [
        "in",
        0.011869463256015907
      ],
      [
        "den",
        0.01170635922239651
      ],
      [
        "von",
        0.011676855635375709
      ],
      [
        "des",
        0.01084317043879214
      ],
      [
        "fuer",
        0.00952264968054209
      ]
    ],
    "33": [
      [
        "sie",
        0.01823121009045235
      ],
      [
        "ich",
        0.015423728646066767
      ],
      [
        "er",
        0.014102173854233218
      ],
      [
        "und",
        0.013684786785520875
      ],
      [
        "zu",
        0.013402195864965707
      ],
      [
        "nicht",
        0.012623317083101625
      ],
      [
        "sich",
        0.011608931176109139
      ],
      [
        "die",
        0.01152198001236975
      ],
      [
        "es",
        0.011193354444970324
      ],
      [
        "der",
        0.01100042778119185
      ]
    ],
    "34": [
      [
        "mai",
        0.01821484007394809
      ],
      [
        "die",
        0.016819261768275532
      ],
      [
        "der",
        0.01556707475332467
      ],
      [
        "und",
        0.012363313652492873
      ],
      [
        "in",
        0.012142022316337694
      ],
      [
        "zu",
        0.011935522789483668
      ],
      [
        "den",
        0.011878499899544192
      ],
      [
        "des",
        0.011195917670923263
      ],
      [
        "von",
        0.010922345526892982
      ],
      [
        "koeln",
        0.010549986389444956
      ]
    ],
    "35": [
      [
        "fr",
        0.026966542510389067
      ],
      [
        "der",
        0.015448481629266486
      ],
      [
        "die",
        0.015386399044739617
      ],
      [
        "rp",
        0.015154856616846
      ],
      [
        "st",
        0.01416287163973095
      ],
      [
        "in",
        0.014008368737715122
      ],
      [
        "und",
        0.013111593111248392
      ],
      [
        "gallen",
        0.012026974113043482
      ],
      [
        "fuer",
        0.011903530630832031
      ],
      [
        "den",
        0.011496809884722282
      ]
    ],
    "36": [
      [
        "auswanderer",
        0.019746562947762995
      ],
      [
        "und",
        0.014952229573789552
      ],
      [
        "die",
        0.013531081370304378
      ],
      [
        "fuer",
        0.013433434096636372
      ],
      [
        "zu",
        0.013097706199491563
      ],
      [
        "in",
        0.013050736648126789
      ],
      [
        "der",
        0.01283189243607292
      ],
      [
        "von",
        0.012815737418931163
      ],
      [
        "nach",
        0.012206933661502689
      ],
      [
        "deutschen",
        0.01174401209831201
      ]
    ],
    "37": [
      [
        "jhro",
        0.023097818499563237
      ],
      [
        "von",
        0.01807584800101475
      ],
      [
        "majest",
        0.018029845352536523
      ],
      [
        "affairen",
        0.017530006468040753
      ],
      [
        "koenigl",
        0.015615450360220613
      ],
      [
        "zu",
        0.015566026671100006
      ],
      [
        "und",
        0.012962946018617418
      ],
      [
        "da",
        0.012951363538891772
      ],
      [
        "man",
        0.012617130562300374
      ],
      [
        "de",
        0.012390317498136277
      ]
    ],
    "38": [
      [
        "die",
        0.01691027346013939
      ],
      [
        "der",
        0.016422943469041138
      ],
      [
        "juni",
        0.01434518410931315
      ],
      [
        "und",
        0.01269668582406534
      ],
      [
        "zu",
        0.01254693279370257
      ],
      [
        "des",
        0.012259920131340954
      ],
      [
        "in",
        0.011850835626331113
      ],
      [
        "den",
        0.011706612747995504
      ],
      [
        "von",
        0.011179235339742048
      ],
      [
        "auf",
        0.009904311857884495
      ]
    ],
    "39": [
      [
        "czernowitz",
        0.01919436043181794
      ],
      [
        "der",
        0.01715698046419269
      ],
      [
        "die",
        0.016046064452675417
      ],
      [
        "in",
        0.013587159728941691
      ],
      [
        "des",
        0.012808926127369889
      ],
      [
        "den",
        0.012070428937746786
      ],
      [
        "und",
        0.011773424670214213
      ],
      [
        "dr",
        0.011285403412412787
      ],
      [
        "cz",
        0.010429760928188219
      ],
      [
        "czernowitzer",
        0.010341048512256146
      ]
    ],
    "40": [
      [
        "nr",
        0.03918421576953639
      ],
      [
        "ich",
        0.02978527913620507
      ],
      [
        "vgl",
        0.017885957260672283
      ],
      [
        "bayreuth",
        0.017500960895996558
      ],
      [
        "jean",
        0.01635076472059991
      ],
      [
        "an",
        0.016240317504126137
      ],
      [
        "berlin",
        0.014581423110429903
      ],
      [
        "mir",
        0.014379430390801579
      ],
      [
        "jp",
        0.014123676699210394
      ],
      [
        "nachtr",
        0.013487757421296764
      ]
    ],
    "41": [
      [
        "der",
        0.016161634741871444
      ],
      [
        "des",
        0.01580208616535202
      ],
      [
        "die",
        0.01517685735196141
      ],
      [
        "in",
        0.014476222768595502
      ],
      [
        "olmuetz",
        0.012802996919006859
      ],
      [
        "und",
        0.012135751895093132
      ],
      [
        "den",
        0.011665880313764492
      ],
      [
        "tetanus",
        0.01062593082531991
      ],
      [
        "deutschen",
        0.010411038311240425
      ],
      [
        "im",
        0.010164062726920666
      ]
    ],
    "42": [
      [
        "die",
        0.015923746162069045
      ],
      [
        "sgr",
        0.01536507840605257
      ],
      [
        "koeln",
        0.0150606185294689
      ],
      [
        "der",
        0.014963960420180595
      ],
      [
        "zu",
        0.013139564656170997
      ],
      [
        "den",
        0.012417317781980063
      ],
      [
        "und",
        0.012100289716728895
      ],
      [
        "in",
        0.012011205712122459
      ],
      [
        "uhr",
        0.011609268955675815
      ],
      [
        "thlr",
        0.011527773543344194
      ]
    ],
    "43": [
      [
        "frauen",
        0.04929804994604542
      ],
      [
        "frauenstimmrecht",
        0.02272855392573153
      ],
      [
        "frau",
        0.022178709726068495
      ],
      [
        "die",
        0.020816682612890516
      ],
      [
        "frauenwahlrecht",
        0.01886568834098907
      ],
      [
        "politischen",
        0.018514600507875408
      ],
      [
        "der",
        0.01848410886205269
      ],
      [
        "das",
        0.018305791398318758
      ],
      [
        "fuer",
        0.016974674725471685
      ],
      [
        "und",
        0.014269724915640143
      ]
    ],
    "44": [
      [
        "die",
        0.016029409396613663
      ],
      [
        "der",
        0.01568729714236106
      ],
      [
        "in",
        0.012503368396511689
      ],
      [
        "den",
        0.01247308126905454
      ],
      [
        "koeln",
        0.012442471402869935
      ],
      [
        "des",
        0.01232210958968473
      ],
      [
        "und",
        0.01208064435666024
      ],
      [
        "zu",
        0.011939471374379285
      ],
      [
        "von",
        0.011170007814338915
      ],
      [
        "auf",
        0.009956243265743504
      ]
    ],
    "45": [
      [
        "und",
        0.015971831276135582
      ],
      [
        "frag",
        0.015739758546462673
      ],
      [
        "da",
        0.013964576990062098
      ],
      [
        "so",
        0.012695290699050002
      ],
      [
        "die",
        0.01236778098501589
      ],
      [
        "zu",
        0.011757968742754395
      ],
      [
        "ein",
        0.011476097640581839
      ],
      [
        "nicht",
        0.011219053328503563
      ],
      [
        "er",
        0.011111639030298288
      ],
      [
        "den",
        0.010338894589399926
      ]
    ],
    "46": [
      [
        "und",
        0.01746579029633665
      ],
      [
        "auch",
        0.01425287651186505
      ],
      [
        "in",
        0.014002122612967427
      ],
      [
        "oder",
        0.012916575767863453
      ],
      [
        "pag",
        0.01265662210505709
      ],
      [
        "wie",
        0.012473640062396632
      ],
      [
        "so",
        0.012287104623828047
      ],
      [
        "von",
        0.011984113427770882
      ],
      [
        "wird",
        0.011868978901311743
      ],
      [
        "au",
        0.011744217948449275
      ]
    ],
    "47": [
      [
        "exped",
        0.029600547674281906
      ],
      [
        "offerten",
        0.028531801194935667
      ],
      [
        "fuer",
        0.026004172653570017
      ],
      [
        "bef",
        0.02110919948298055
      ],
      [
        "gesucht",
        0.02038174315623677
      ],
      [
        "arbeitg",
        0.019791688939277224
      ],
      [
        "arbeitgeber",
        0.017882086989876794
      ],
      [
        "unter",
        0.01698815308380907
      ],
      [
        "geschaeft",
        0.01488548707186216
      ],
      [
        "eine",
        0.014282242851307815
      ]
    ],
    "48": [
      [
        "der",
        0.017763901782095783
      ],
      [
        "dr",
        0.01698829857410746
      ],
      [
        "wien",
        0.0157847099147424
      ],
      [
        "die",
        0.015762962241185462
      ],
      [
        "des",
        0.014511286355811087
      ],
      [
        "in",
        0.013749722379611763
      ],
      [
        "den",
        0.012511769028398255
      ],
      [
        "und",
        0.01206462370232945
      ],
      [
        "fuer",
        0.01047350232610922
      ],
      [
        "detto",
        0.010050598244307377
      ]
    ],
    "49": [
      [
        "ich",
        0.01866514658416131
      ],
      [
        "er",
        0.017141563756038043
      ],
      [
        "und",
        0.01442546193624851
      ],
      [
        "zu",
        0.013291816635250408
      ],
      [
        "da",
        0.012982541726363678
      ],
      [
        "mir",
        0.011289545132762913
      ],
      [
        "nicht",
        0.011238364194661298
      ],
      [
        "so",
        0.010888151186139066
      ],
      [
        "die",
        0.01076614797004443
      ],
      [
        "sich",
        0.010756108415852639
      ]
    ],
    "50": [
      [
        "ich",
        0.022114967027113137
      ],
      [
        "sie",
        0.01663443228804649
      ],
      [
        "und",
        0.013886128859692046
      ],
      [
        "nicht",
        0.012626727464717219
      ],
      [
        "er",
        0.01230032502521587
      ],
      [
        "da",
        0.012187388427472048
      ],
      [
        "es",
        0.011914436840704477
      ],
      [
        "die",
        0.011792925129448403
      ],
      [
        "der",
        0.010806058572509216
      ],
      [
        "so",
        0.0107293273504516
      ]
    ],
    "51": [
      [
        "die",
        0.01559683731899891
      ],
      [
        "der",
        0.015451197957375745
      ],
      [
        "zu",
        0.013979254220705598
      ],
      [
        "von",
        0.012859430137641651
      ],
      [
        "des",
        0.012609253626615545
      ],
      [
        "und",
        0.012475482439306072
      ],
      [
        "in",
        0.011992855586047017
      ],
      [
        "den",
        0.011686910058665099
      ],
      [
        "da",
        0.010702245759797675
      ],
      [
        "auf",
        0.010121626615100163
      ]
    ],
    "52": [
      [
        "die",
        0.014191942494818902
      ],
      [
        "und",
        0.013970287333966679
      ],
      [
        "der",
        0.013200221835543964
      ],
      [
        "den",
        0.011623760568985423
      ],
      [
        "sie",
        0.010380207797513231
      ],
      [
        "in",
        0.010243748667421327
      ],
      [
        "ich",
        0.010229850208518285
      ],
      [
        "auf",
        0.010107148805449486
      ],
      [
        "zu",
        0.010084219754497229
      ],
      [
        "von",
        0.00983256252977849
      ]
    ],
    "53": [
      [
        "der",
        0.014006708387212796
      ],
      [
        "die",
        0.01346724720763271
      ],
      [
        "und",
        0.012788773919540171
      ],
      [
        "von",
        0.012075317079748035
      ],
      [
        "kugel",
        0.01189614060468038
      ],
      [
        "in",
        0.011837801502944981
      ],
      [
        "des",
        0.011731046440998764
      ],
      [
        "zu",
        0.010998780711349089
      ],
      [
        "so",
        0.01089044866180569
      ],
      [
        "dem",
        0.00981525582502614
      ]
    ],
    "54": [
      [
        "und",
        0.015435626662397294
      ],
      [
        "auswanderer",
        0.015152410311341423
      ],
      [
        "cpt",
        0.01373670661238739
      ],
      [
        "von",
        0.01360807030655166
      ],
      [
        "fuer",
        0.013234361972336618
      ],
      [
        "in",
        0.012675454182527168
      ],
      [
        "newyork",
        0.012572460114417964
      ],
      [
        "der",
        0.012473893943089565
      ],
      [
        "die",
        0.012473526778133502
      ],
      [
        "nach",
        0.011939380739877006
      ]
    ],
    "55": [
      [
        "der",
        0.01549133011989726
      ],
      [
        "die",
        0.014651555807289175
      ],
      [
        "den",
        0.01310877414012929
      ],
      [
        "er",
        0.011132768523563867
      ],
      [
        "des",
        0.010601987830135136
      ],
      [
        "in",
        0.010032977569364727
      ],
      [
        "und",
        0.009948321653323267
      ],
      [
        "ein",
        0.009384377155452624
      ],
      [
        "dem",
        0.00930782186304146
      ],
      [
        "ii",
        0.00917259220712972
      ]
    ],
    "56": [
      [
        "tab",
        0.02840756565002107
      ],
      [
        "rc",
        0.018735992862445264
      ],
      [
        "bey",
        0.016800266315616215
      ],
      [
        "fr",
        0.015791271796651626
      ],
      [
        "theils",
        0.014218279060279579
      ],
      [
        "engl",
        0.01393587105877039
      ],
      [
        "meist",
        0.01311895602508178
      ],
      [
        "der",
        0.012848015955547373
      ],
      [
        "in",
        0.012746500912744917
      ],
      [
        "die",
        0.01215608279643691
      ]
    ],
    "57": [
      [
        "die",
        0.01843215507620733
      ],
      [
        "der",
        0.016658342759202006
      ],
      [
        "ist",
        0.014778545320084116
      ],
      [
        "eine",
        0.014198281298124343
      ],
      [
        "in",
        0.013768048323158274
      ],
      [
        "von",
        0.012912086879798631
      ],
      [
        "so",
        0.012715189740242255
      ],
      [
        "vorstellungen",
        0.01237579978566755
      ],
      [
        "wenn",
        0.012179740221857525
      ],
      [
        "und",
        0.011962999631236317
      ]
    ],
    "58": [
      [
        "die",
        0.016540019057216748
      ],
      [
        "der",
        0.01457996856511123
      ],
      [
        "und",
        0.013811270683788884
      ],
      [
        "ist",
        0.012237650223581685
      ],
      [
        "den",
        0.012030276390080826
      ],
      [
        "das",
        0.011884125558702975
      ],
      [
        "dass",
        0.01171490355138459
      ],
      [
        "des",
        0.010732889989589989
      ],
      [
        "in",
        0.010596250323884246
      ],
      [
        "aber",
        0.010195251844481158
      ]
    ],
    "59": [
      [
        "und",
        0.016376757143114623
      ],
      [
        "der",
        0.0138618079406828
      ],
      [
        "die",
        0.012718526167509092
      ],
      [
        "zu",
        0.012281949144166405
      ],
      [
        "man",
        0.01191798203990096
      ],
      [
        "in",
        0.011050317842360245
      ],
      [
        "da",
        0.010561852356142652
      ],
      [
        "auf",
        0.010392361015421169
      ],
      [
        "oder",
        0.010117301484234942
      ],
      [
        "nicht",
        0.010115599318455895
      ]
    ],
    "60": [
      [
        "ii",
        0.03168200080503137
      ],
      [
        "lat",
        0.017197638509915663
      ],
      [
        "holl",
        0.01670929665711952
      ],
      [
        "harrebomee",
        0.016319514627013556
      ],
      [
        "lehmann",
        0.01508001786801683
      ],
      [
        "simrock",
        0.0142944221214363
      ],
      [
        "petri",
        0.014213427170957095
      ],
      [
        "ist",
        0.013475573120268904
      ],
      [
        "wer",
        0.013326793969544119
      ],
      [
        "de",
        0.0130520448521162
      ]
    ],
    "61": [
      [
        "der",
        0.015721379496858406
      ],
      [
        "die",
        0.014710663121182285
      ],
      [
        "und",
        0.013049969465946401
      ],
      [
        "des",
        0.01304178059322706
      ],
      [
        "den",
        0.012655683045719662
      ],
      [
        "von",
        0.012632759846350679
      ],
      [
        "zu",
        0.012412757838207061
      ],
      [
        "in",
        0.012323865617847894
      ],
      [
        "auf",
        0.011055549463024136
      ],
      [
        "im",
        0.008894464846480807
      ]
    ]
  },
  "topics": [
    0,
    0,
    0,
    0,
    0,
    -1,
    0,
    0,
    0,
    0,
    0,
    0,
    0,
    0,
    -1,
    0,
    0,
    0,
    -1,
    0,
    0,
    -1,
    -1,
    -1,
    0,
    0,
    0,
    0,
    0,
    0,
    0,
    0,
    0,
    0,
    0,
    0,
    -1,
    0,
    0,
    0,
    3,
    0,
    -1,
    0,
    0,
    3,
    0,
    0,
    0,
    0,
    -1,
    0,
    0,
    0,
    -1,
    0,
    -1,
    0,
    0,
    0,
    -1,
    0,
    -1,
    0,
    0,
    0,
    -1,
    0,
    0,
    -1,
    0,
    0,
    0,
    0,
    0,
    -1,
    0,
    0,
    0,
    0,
    -1,
    0,
    -1,
    0,
    0,
    -1,
    0,
    -1,
    0,
    -1,
    0,
    0,
    0,
    0,
    0,
    0,
    0,
    0,
    0,
    -1,
    0,
    -1,
    0,
    -1,
    0,
    0,
    0,
    0,
    0,
    0,
    0,
    0,
    0,
    0,
    -1,
    0,
    -1,
    0,
    0,
    -1,
    0,
    0,
    -1,
    0,
    0,
    -1,
    0,
    0,
    0,
    0,
    0,
    0,
    0,
    -1,
    0,
    0,
    0,
    0,
    -1,
    0,
    -1,
    0,
    -1,
    0,
    0,
    0,
    0,
    0,
    0,
    0,
    0,
    0,
    0,
    0,
    0,
    -1,
    -1,
    0,
    0,
    0,
    0,
    0,
    0,
    3,
    0,
    0,
    0,
    0,
    0,
    0,
    0,
    0,
    0,
    -1,
    0,
    0,
    0,
    0,
    0,
    0,
    0,
    0,
    0,
    0,
    0,
    0,
    0,
    -1,
    0,
    0,
    0,
    0,
    0,
    0,
    0,
    0,
    0,
    0,
    0,
    0,
    0,
    0,
    0,
    0,
    0,
    0,
    0,
    0,
    0,
    0,
    0,
    0,
    0,
    0,
    0,
    0,
    0,
    0,
    -1,
    3,
    0,
    0,
    0,
    0,
    0,
    0,
    -1,
    0,
    0,
    -1,
    0,
    0,
    0,
    0,
    0,
    0,
    0,
    0,
    0,
    0,
    -1,
    0,
    0,
    0,
    0,
    0,
    0,
    0,
    -1,
    0,
    0,
    0,
    0,
    0,
    0,
    0,
    0,
    0,
    -1,
    0,
    0,
    0,
    0,
    0,
    0,
    0,
    -1,
    -1,
    0,
    0,
    0,
    0,
    0,
    -1,
    0,
    0,
    0,
    0,
    0,
    0,
    0,
    0,
    0,
    0,
    0,
    0,
    0,
    0,
    0,
    0,
    0,
    0,
    0,
    -1,
    0,
    0,
    0,
    0,
    0,
    0,
    0,
    0,
    0,
    0,
    0,
    0,
    0,
    0,
    0,
    0,
    0,
    0,
    0,
    0,
    3,
    0,
    0,
    0,
    0,
    0,
    0,
    0,
    0,
    -1,
    0,
    0,
    0,
    0,
    0,
    -1,
    0,
    -1,
    0,
    -1,
    0,
    0,
    0,
    0,
    0,
    -1,
    -1,
    -1,
    -1,
    0,
    -1,
    0,
    -1,
    0,
    0,
    0,
    0,
    0,
    -1,
    0,
    0,
    -1,
    -1,
    0,
    0,
    -1,
    0,
    -1,
    0,
    -1,
    0,
    0,
    0,
    0,
    0,
    0,
    -1,
    0,
    -1,
    0,
    0,
    3,
    0,
    0,
    0,
    0,
    0,
    0,
    0,
    -1,
    0,
    0,
    0,
    0,
    0,
    0,
    0,
    -1,
    -1,
    0,
    0,
    0,
    0,
    0,
    0,
    0,
    0,
    0,
    -1,
    0,
    0,
    0,
    0,
    0,
    0,
    0,
    0,
    0,
    0,
    0,
    0,
    0,
    0,
    0,
    0,
    0,
    0,
    -1,
    -1,
    0,
    0,
    0,
    0,
    -1,
    0,
    0,
    0,
    0,
    0,
    0,
    0,
    0,
    0,
    -1,
    0,
    0,
    0,
    0,
    3,
    -1,
    0,
    -1,
    0,
    -1,
    15,
    -1,
    -1,
    -1,
    -1,
    0,
    -1,
    3,
    -1,
    -1,
    -1,
    -1,
    7,
    -1,
    5,
    -1,
    12,
    -1,
    5,
    -1,
    -1,
    0,
    -1,
    0,
    3,
    -1,
    -1,
    0,
    -1,
    -1,
    0,
    29,
    3,
    0,
    0,
    0,
    0,
    -1,
    50,
    -1,
    9,
    -1,
    -1,
    24,
    -1,
    -1,
    0,
    0,
    0,
    -1,
    -1,
    -1,
    5,
    1,
    1,
    1,
    -1,
    1,
    -1,
    1,
    -1,
    19,
    4,
    23,
    23,
    -1,
    -1,
    -1,
    4,
    -1,
    -1,
    -1,
    4,
    4,
    -1,
    4,
    4,
    4,
    -1,
    -1,
    -1,
    23,
    -1,
    23,
    23,
    19,
    -1,
    -1,
    23,
    4,
    -1,
    -1,
    -1,
    4,
    4,
    -1,
    4,
    44,
    -1,
    -1,
    23,
    4,
    4,
    23,
    23,
    4,
    4,
    -1,
    -1,
    -1,
    4,
    23,
    4,
    23,
    4,
    4,
    -1,
    4,
    -1,
    19,
    -1,
    -1,
    4,
    23,
    -1,
    21,
    38,
    4,
    61,
    -1,
    -1,
    4,
    -1,
    -1,
    -1,
    4,
    4,
    4,
    4,
    23,
    4,
    -1,
    51,
    23,
    -1,
    4,
    4,
    -1,
    -1,
    -1,
    23,
    -1,
    51,
    4,
    -1,
    51,
    23,
    4,
    4,
    -1,
    51,
    4,
    -1,
    4,
    23,
    -1,
    -1,
    -1,
    51,
    -1,
    -1,
    -1,
    -1,
    4,
    23,
    4,
    4,
    4,
    4,
    4,
    -1,
    -1,
    4,
    4,
    25,
    23,
    -1,
    -1,
    4,
    4,
    4,
    4,
    4,
    4,
    -1,
    4,
    4,
    4,
    2,
    23,
    23,
    4,
    -1,
    4,
    4,
    4,
    -1,
    -1,
    -1,
    4,
    4,
    4,
    -1,
    -1,
    23,
    -1,
    -1,
    38,
    4,
    4,
    4,
    -1,
    4,
    4,
    4,
    4,
    4,
    4,
    4,
    4,
    4,
    -1,
    4,
    4,
    38,
    -1,
    -1,
    44,
    23,
    4,
    4,
    4,
    -1,
    0,
    -1,
    -1,
    -1,
    -1,
    -1,
    6,
    -1,
    -1,
    -1,
    -1,
    -1,
    43,
    -1,
    -1,
    -1,
    -1,
    0,
    0,
    -1,
    51,
    -1,
    -1,
    -1,
    -1,
    -1,
    -1,
    0,
    59,
    -1,
    0,
    -1,
    -1,
    0,
    -1,
    -1,
    0,
    43,
    2,
    43,
    -1,
    45,
    -1,
    5,
    -1,
    -1,
    -1,
    7,
    -1,
    -1,
    7,
    7,
    -1,
    -1,
    -1,
    -1,
    9,
    0,
    45,
    -1,
    -1,
    0,
    45,
    -1,
    7,
    -1,
    -1,
    -1,
    -1,
    -1,
    -1,
    -1,
    -1,
    -1,
    -1,
    12,
    -1,
    -1,
    -1,
    -1,
    -1,
    -1,
    -1,
    -1,
    -1,
    -1,
    15,
    15,
    -1,
    -1,
    0,
    0,
    0,
    -1,
    -1,
    -1,
    -1,
    2,
    12,
    -1,
    12,
    12,
    56,
    -1,
    56,
    0,
    -1,
    52,
    -1,
    12,
    12,
    12,
    -1,
    -1,
    -1,
    -1,
    -1,
    -1,
    56,
    -1,
    56,
    56,
    7,
    -1,
    -1,
    7,
    7,
    7,
    7,
    -1,
    -1,
    12,
    12,
    33,
    50,
    -1,
    -1,
    9,
    9,
    9,
    9,
    9,
    9,
    9,
    9,
    9,
    9,
    9,
    9,
    7,
    -1,
    3,
    -1,
    -1,
    -1,
    -1,
    -1,
    -1,
    -1,
    -1,
    -1,
    0,
    -1,
    -1,
    53,
    20,
    20,
    -1,
    -1,
    -1,
    -1,
    -1,
    -1,
    15,
    -1,
    15,
    6,
    0,
    -1,
    0,
    -1,
    -1,
    0,
    0,
    0,
    0,
    0,
    32,
    -1,
    0,
    0,
    0,
    0,
    -1,
    6,
    0,
    24,
    -1,
    -1,
    0,
    0,
    0,
    -1,
    29,
    0,
    0,
    0,
    0,
    -1,
    -1,
    -1,
    -1,
    -1,
    -1,
    -1,
    -1,
    -1,
    -1,
    -1,
    -1,
    0,
    13,
    13,
    -1,
    -1,
    -1,
    0,
    0,
    0,
    0,
    0,
    0,
    -1,
    5,
    -1,
    24,
    29,
    -1,
    29,
    -1,
    -1,
    -1,
    0,
    12,
    -1,
    -1,
    7,
    -1,
    12,
    -1,
    -1,
    9,
    -1,
    3,
    3,
    -1,
    33,
    0,
    -1,
    0,
    0,
    29,
    -1,
    12,
    12,
    -1,
    -1,
    0,
    -1,
    -1,
    -1,
    5,
    30,
    0,
    15,
    -1,
    -1,
    11,
    -1,
    9,
    9,
    -1,
    -1,
    -1,
    -1,
    9,
    0,
    0,
    0,
    0,
    -1,
    0,
    1,
    -1,
    15,
    -1,
    -1,
    0,
    0,
    0,
    0,
    -1,
    -1,
    -1,
    -1,
    -1,
    -1,
    0,
    0,
    -1,
    -1,
    -1,
    3,
    0,
    3,
    -1,
    0,
    3,
    -1,
    -1,
    33,
    -1,
    -1,
    0,
    -1,
    -1,
    0,
    -1,
    -1,
    -1,
    5,
    -1,
    -1,
    -1,
    -1,
    -1,
    -1,
    -1,
    -1,
    -1,
    5,
    -1,
    55,
    7,
    -1,
    -1,
    7,
    -1,
    -1,
    -1,
    -1,
    -1,
    29,
    29,
    -1,
    29,
    24,
    -1,
    24,
    -1,
    3,
    0,
    3,
    -1,
    3,
    -1,
    -1,
    -1,
    -1,
    14,
    0,
    0,
    7,
    -1,
    29,
    5,
    -1,
    -1,
    -1,
    0,
    -1,
    5,
    -1,
    -1,
    -1,
    -1,
    -1,
    23,
    -1,
    -1,
    -1,
    -1,
    0,
    15,
    -1,
    -1,
    -1,
    0,
    0,
    -1,
    60,
    -1,
    -1,
    -1,
    -1,
    0,
    -1,
    -1,
    0,
    7,
    -1,
    57,
    -1,
    0,
    0,
    0,
    0,
    0,
    -1,
    -1,
    0,
    0,
    -1,
    -1,
    -1,
    0,
    0,
    3,
    0,
    3,
    -1,
    -1,
    0,
    -1,
    -1,
    -1,
    -1,
    3,
    -1,
    58,
    -1,
    -1,
    -1,
    0,
    -1,
    -1,
    -1,
    -1,
    -1,
    -1,
    -1,
    -1,
    -1,
    -1,
    -1,
    -1,
    -1,
    5,
    -1,
    -1,
    -1,
    -1,
    -1,
    50,
    -1,
    -1,
    57,
    9,
    0,
    -1,
    12,
    5,
    13,
    0,
    0,
    0,
    -1,
    -1,
    2,
    -1,
    -1,
    0,
    -1,
    -1,
    -1,
    -1,
    -1,
    15,
    -1,
    5,
    30,
    -1,
    -1,
    -1,
    -1,
    -1,
    -1,
    -1,
    -1,
    -1,
    -1,
    -1,
    0,
    -1,
    -1,
    0,
    -1,
    3,
    0,
    -1,
    -1,
    -1,
    -1,
    -1,
    -1,
    -1,
    -1,
    -1,
    -1,
    59,
    7,
    -1,
    -1,
    -1,
    -1,
    -1,
    0,
    -1,
    -1,
    -1,
    -1,
    -1,
    -1,
    -1,
    -1,
    -1,
    -1,
    -1,
    -1,
    -1,
    -1,
    -1,
    29,
    -1,
    -1,
    -1,
    0,
    5,
    27,
    -1,
    0,
    0,
    3,
    -1,
    -1,
    0,
    -1,
    -1,
    0,
    52,
    -1,
    -1,
    -1,
    -1,
    24,
    -1,
    24,
    -1,
    -1,
    -1,
    -1,
    -1,
    -1,
    1,
    58,
    -1,
    33,
    5,
    5,
    -1,
    -1,
    0,
    -1,
    5,
    5,
    -1,
    -1,
    9,
    -1,
    9,
    -1,
    15,
    0,
    -1,
    13,
    29,
    12,
    -1,
    33,
    -1,
    -1,
    -1,
    -1,
    -1,
    0,
    -1,
    -1,
    5,
    3,
    3,
    0,
    -1,
    3,
    3,
    -1,
    -1,
    3,
    -1,
    0,
    3,
    -1,
    -1,
    -1,
    3,
    5,
    -1,
    2,
    -1,
    12,
    0,
    0,
    0,
    0,
    27,
    -1,
    -1,
    0,
    -1,
    -1,
    -1,
    -1,
    0,
    1,
    1,
    -1,
    -1,
    -1,
    33,
    -1,
    -1,
    -1,
    5,
    12,
    -1,
    12,
    -1,
    9,
    -1,
    -1,
    -1,
    -1,
    -1,
    -1,
    -1,
    -1,
    -1,
    -1,
    -1,
    -1,
    30,
    30,
    30,
    5,
    -1,
    -1,
    7,
    -1,
    11,
    0,
    -1,
    0,
    9,
    9,
    9,
    5,
    11,
    0,
    -1,
    -1,
    9,
    3,
    3,
    -1,
    -1,
    -1,
    -1,
    -1,
    -1,
    -1,
    -1,
    -1,
    25,
    -1,
    -1,
    0,
    32,
    -1,
    22,
    -1,
    -1,
    22,
    2,
    -1,
    -1,
    32,
    3,
    22,
    -1,
    -1,
    4,
    -1,
    -1,
    -1,
    -1,
    -1,
    -1,
    -1,
    -1,
    25,
    -1,
    -1,
    -1,
    -1,
    25,
    -1,
    -1,
    25,
    25,
    -1,
    -1,
    -1,
    -1,
    22,
    -1,
    -1,
    -1,
    25,
    -1,
    -1,
    -1,
    -1,
    22,
    -1,
    -1,
    -1,
    22,
    -1,
    22,
    -1,
    -1,
    -1,
    25,
    -1,
    -1,
    -1,
    -1,
    -1,
    -1,
    -1,
    -1,
    25,
    -1,
    -1,
    25,
    -1,
    -1,
    -1,
    -1,
    -1,
    -1,
    -1,
    -1,
    22,
    -1,
    -1,
    -1,
    -1,
    -1,
    -1,
    -1,
    -1,
    -1,
    -1,
    -1,
    -1,
    -1,
    -1,
    -1,
    -1,
    -1,
    -1,
    -1,
    4,
    -1,
    19,
    -1,
    16,
    25,
    25,
    -1,
    37,
    -1,
    -1,
    -1,
    2,
    22,
    25,
    2,
    -1,
    51,
    37,
    51,
    37,
    -1,
    -1,
    -1,
    -1,
    2,
    37,
    -1,
    25,
    -1,
    16,
    37,
    -1,
    37,
    -1,
    37,
    -1,
    37,
    37,
    37,
    -1,
    37,
    -1,
    37,
    37,
    -1,
    37,
    37,
    37,
    -1,
    -1,
    -1,
    22,
    25,
    -1,
    -1,
    22,
    37,
    4,
    -1,
    -1,
    22,
    -1,
    22,
    -1,
    -1,
    -1,
    22,
    -1,
    -1,
    -1,
    22,
    22,
    16,
    -1,
    -1,
    -1,
    -1,
    -1,
    -1,
    -1,
    22,
    25,
    -1,
    51,
    22,
    -1,
    22,
    -1,
    -1,
    22,
    -1,
    -1,
    25,
    22,
    25,
    22,
    22,
    -1,
    -1,
    25,
    -1,
    29,
    -1,
    -1,
    -1,
    -1,
    -1,
    15,
    15,
    -1,
    9,
    -1,
    -1,
    -1,
    0,
    0,
    5,
    7,
    -1,
    -1,
    7,
    -1,
    0,
    -1,
    -1,
    -1,
    15,
    57,
    15,
    -1,
    -1,
    50,
    -1,
    -1,
    0,
    -1,
    -1,
    -1,
    -1,
    7,
    -1,
    -1,
    -1,
    -1,
    -1,
    52,
    52,
    -1,
    -1,
    24,
    -1,
    -1,
    -1,
    12,
    9,
    9,
    -1,
    0,
    0,
    0,
    0,
    0,
    0,
    -1,
    43,
    -1,
    2,
    2,
    -1,
    -1,
    24,
    7,
    5,
    -1,
    0,
    -1,
    -1,
    -1,
    -1,
    50,
    -1,
    -1,
    15,
    15,
    15,
    15,
    -1,
    -1,
    2,
    -1,
    5,
    9,
    -1,
    -1,
    29,
    29,
    29,
    29,
    -1,
    29,
    0,
    -1,
    -1,
    7,
    -1,
    -1,
    -1,
    24,
    -1,
    0,
    -1,
    31,
    24,
    -1,
    45,
    0,
    -1,
    -1,
    5,
    -1,
    -1,
    -1,
    -1,
    0,
    -1,
    7,
    1,
    33,
    -1,
    -1,
    5,
    52,
    -1,
    -1,
    -1,
    -1,
    12,
    -1,
    -1,
    0,
    3,
    3,
    -1,
    -1,
    -1,
    -1,
    -1,
    -1,
    -1,
    -1,
    -1,
    -1,
    4,
    0,
    5,
    -1,
    30,
    20,
    30,
    20,
    20,
    3,
    -1,
    31,
    -1,
    -1,
    20,
    31,
    -1,
    30,
    30,
    -1,
    4,
    7,
    -1,
    -1,
    20,
    13,
    25,
    31,
    20,
    30,
    20,
    -1,
    31,
    60,
    3,
    30,
    7,
    -1,
    -1,
    3,
    30,
    -1,
    30,
    -1,
    -1,
    -1,
    31,
    -1,
    -1,
    -1,
    25,
    -1,
    -1,
    0,
    30,
    -1,
    -1,
    -1,
    1,
    3,
    12,
    -1,
    0,
    -1,
    -1,
    -1,
    -1,
    20,
    -1,
    0,
    -1,
    20,
    20,
    20,
    -1,
    0,
    20,
    -1,
    30,
    -1,
    3,
    -1,
    20,
    31,
    -1,
    -1,
    -1,
    3,
    0,
    31,
    20,
    -1,
    20,
    20,
    25,
    13,
    -1,
    -1,
    -1,
    -1,
    -1,
    22,
    12,
    20,
    -1,
    -1,
    -1,
    30,
    3,
    -1,
    31,
    -1,
    -1,
    -1,
    -1,
    -1,
    -1,
    -1,
    20,
    -1,
    -1,
    -1,
    -1,
    16,
    56,
    31,
    -1,
    30,
    -1,
    -1,
    -1,
    45,
    -1,
    3,
    7,
    -1,
    3,
    3,
    31,
    -1,
    -1,
    -1,
    -1,
    31,
    -1,
    -1,
    -1,
    31,
    3,
    3,
    20,
    3,
    -1,
    2,
    3,
    -1,
    -1,
    3,
    31,
    -1,
    1,
    -1,
    7,
    24,
    -1,
    -1,
    -1,
    -1,
    -1,
    -1,
    -1,
    3,
    31,
    20,
    4,
    -1,
    -1,
    -1,
    -1,
    29,
    -1,
    -1,
    -1,
    -1,
    -1,
    5,
    -1,
    -1,
    -1,
    -1,
    0,
    45,
    -1,
    -1,
    -1,
    1,
    -1,
    -1,
    40,
    40,
    40,
    40,
    40,
    40,
    40,
    40,
    40,
    -1,
    -1,
    -1,
    -1,
    0,
    3,
    -1,
    -1,
    0,
    -1,
    -1,
    -1,
    5,
    7,
    7,
    -1,
    -1,
    -1,
    0,
    0,
    5,
    -1,
    -1,
    -1,
    -1,
    -1,
    -1,
    -1,
    -1,
    2,
    -1,
    24,
    -1,
    -1,
    -1,
    -1,
    3,
    -1,
    -1,
    0,
    -1,
    -1,
    -1,
    -1,
    20,
    -1,
    -1,
    5,
    5,
    -1,
    -1,
    2,
    43,
    2,
    -1,
    -1,
    0,
    0,
    -1,
    3,
    -1,
    -1,
    0,
    0,
    0,
    -1,
    3,
    -1,
    -1,
    15,
    15,
    -1,
    0,
    -1,
    -1,
    0,
    24,
    -1,
    0,
    -1,
    -1,
    1,
    -1,
    -1,
    -1,
    -1,
    -1,
    -1,
    -1,
    -1,
    53,
    -1,
    -1,
    0,
    17,
    0,
    -1,
    -1,
    -1,
    -1,
    -1,
    -1,
    -1,
    -1,
    -1,
    -1,
    12,
    31,
    -1,
    -1,
    -1,
    5,
    5,
    5,
    -1,
    0,
    -1,
    -1,
    -1,
    9,
    -1,
    1,
    -1,
    0,
    -1,
    -1,
    -1,
    -1,
    30,
    -1,
    -1,
    -1,
    -1,
    -1,
    -1,
    -1,
    0,
    0,
    2,
    0,
    -1,
    5,
    -1,
    -1,
    5,
    1,
    5,
    -1,
    5,
    5,
    -1,
    -1,
    -1,
    -1,
    9,
    -1,
    15,
    -1,
    -1,
    -1,
    -1,
    11,
    -1,
    -1,
    0,
    0,
    -1,
    51,
    -1,
    2,
    7,
    7,
    -1,
    0,
    20,
    -1,
    -1,
    -1,
    -1,
    0,
    0,
    24,
    -1,
    -1,
    -1,
    -1,
    59,
    -1,
    -1,
    -1,
    3,
    -1,
    -1,
    -1,
    -1,
    6,
    13,
    -1,
    -1,
    -1,
    -1,
    -1,
    12,
    59,
    -1,
    -1,
    -1,
    0,
    -1,
    -1,
    -1,
    -1,
    0,
    -1,
    45,
    0,
    -1,
    55,
    7,
    0,
    -1,
    -1,
    -1,
    50,
    -1,
    -1,
    5,
    0,
    0,
    -1,
    -1,
    30,
    12,
    30,
    2,
    9,
    3,
    -1,
    3,
    2,
    -1,
    -1,
    -1,
    52,
    20,
    20,
    20,
    -1,
    -1,
    1,
    3,
    0,
    0,
    0,
    3,
    0,
    0,
    -1,
    -1,
    0,
    -1,
    0,
    3,
    0,
    0,
    5,
    3,
    -1,
    -1,
    0,
    0,
    -1,
    -1,
    5,
    -1,
    0,
    24,
    12,
    0,
    -1,
    0,
    0,
    0,
    0,
    -1,
    -1,
    0,
    -1,
    0,
    -1,
    0,
    0,
    -1,
    0,
    -1,
    0,
    0,
    -1,
    -1,
    3,
    -1,
    -1,
    0,
    0,
    -1,
    0,
    0,
    3,
    -1,
    -1,
    0,
    -1,
    0,
    -1,
    -1,
    -1,
    -1,
    -1,
    -1,
    0,
    -1,
    -1,
    -1,
    2,
    -1,
    -1,
    -1,
    -1,
    -1,
    -1,
    0,
    15,
    15,
    -1,
    5,
    -1,
    13,
    0,
    0,
    -1,
    33,
    5,
    -1,
    -1,
    -1,
    -1,
    -1,
    -1,
    3,
    -1,
    -1,
    -1,
    -1,
    -1,
    -1,
    12,
    9,
    0,
    -1,
    0,
    0,
    -1,
    5,
    2,
    -1,
    -1,
    -1,
    -1,
    -1,
    0,
    0,
    0,
    52,
    0,
    -1,
    -1,
    0,
    9,
    -1,
    5,
    7,
    3,
    0,
    -1,
    -1,
    -1,
    -1,
    -1,
    -1,
    -1,
    -1,
    0,
    53,
    -1,
    -1,
    6,
    13,
    -1,
    -1,
    9,
    49,
    -1,
    -1,
    49,
    49,
    49,
    49,
    -1,
    -1,
    49,
    -1,
    -1,
    49,
    -1,
    -1,
    49,
    -1,
    -1,
    49,
    -1,
    45,
    49,
    -1,
    -1,
    49,
    -1,
    -1,
    49,
    -1,
    -1,
    -1,
    -1,
    -1,
    -1,
    -1,
    -1,
    -1,
    -1,
    -1,
    -1,
    -1,
    -1,
    5,
    0,
    5,
    -1,
    -1,
    12,
    -1,
    -1,
    -1,
    -1,
    -1,
    -1,
    58,
    -1,
    24,
    -1,
    -1,
    3,
    -1,
    -1,
    -1,
    0,
    0,
    0,
    -1,
    -1,
    -1,
    -1,
    -1,
    33,
    -1,
    -1,
    -1,
    45,
    -1,
    3,
    -1,
    -1,
    7,
    -1,
    24,
    -1,
    -1,
    -1,
    -1,
    -1,
    7,
    -1,
    -1,
    0,
    -1,
    -1,
    -1,
    33,
    -1,
    -1,
    -1,
    -1,
    -1,
    -1,
    0,
    -1,
    -1,
    -1,
    0,
    0,
    0,
    0,
    53,
    0,
    14,
    14,
    14,
    14,
    14,
    14,
    14,
    14,
    14,
    14,
    14,
    14,
    14,
    14,
    47,
    47,
    47,
    47,
    47,
    47,
    47,
    47,
    47,
    47,
    47,
    47,
    47,
    13,
    6,
    13,
    13,
    13,
    13,
    13,
    13,
    27,
    13,
    -1,
    13,
    13,
    14,
    36,
    36,
    54,
    54,
    54,
    36,
    54,
    54,
    54,
    54,
    54,
    54,
    36,
    54,
    36,
    54,
    36,
    36,
    36,
    36,
    36,
    36,
    36,
    36,
    36,
    36,
    36,
    36,
    36,
    14,
    14,
    14,
    14,
    14,
    14,
    14,
    14,
    14,
    -1,
    46,
    14,
    14,
    -1,
    14,
    14,
    46,
    14,
    46,
    14,
    46,
    46,
    46,
    -1,
    46,
    -1,
    46,
    46,
    46,
    14,
    46,
    14,
    46,
    14,
    -1,
    14,
    -1,
    -1,
    -1,
    6,
    6,
    6,
    6,
    6,
    6,
    6,
    6,
    6,
    6,
    6,
    6,
    6,
    6,
    6,
    6,
    6,
    6,
    6,
    6,
    6,
    6,
    6,
    6,
    6,
    6,
    6,
    6,
    6,
    6,
    6,
    6,
    6,
    6,
    6,
    6,
    6,
    6,
    6,
    6,
    6,
    6,
    6,
    6,
    6,
    6,
    6,
    6,
    6,
    6,
    6,
    6,
    6,
    6,
    6,
    6,
    6,
    6,
    6,
    6,
    6,
    6,
    6,
    6,
    6,
    6,
    6,
    6,
    6,
    6,
    6,
    6,
    6,
    6,
    -1,
    -1,
    -1,
    -1,
    -1,
    -1,
    -1,
    -1,
    -1,
    -1,
    0,
    -1,
    0,
    -1,
    39,
    39,
    39,
    28,
    28,
    39,
    39,
    44,
    39,
    28,
    28,
    28,
    17,
    28,
    28,
    28,
    28,
    28,
    28,
    28,
    28,
    28,
    28,
    28,
    28,
    28,
    28,
    28,
    28,
    39,
    39,
    39,
    39,
    39,
    39,
    39,
    39,
    39,
    0,
    -1,
    25,
    0,
    0,
    -1,
    -1,
    3,
    -1,
    53,
    0,
    -1,
    0,
    0,
    0,
    -1,
    -1,
    -1,
    -1,
    -1,
    4,
    17,
    17,
    17,
    17,
    17,
    17,
    17,
    41,
    -1,
    41,
    17,
    17,
    17,
    -1,
    41,
    41,
    17,
    17,
    17,
    41,
    17,
    17,
    17,
    -1,
    41,
    17,
    17,
    17,
    41,
    17,
    17,
    41,
    17,
    41,
    -1,
    41,
    -1,
    17,
    -1,
    17,
    17,
    41,
    41,
    17,
    41,
    10,
    10,
    10,
    10,
    10,
    10,
    10,
    10,
    10,
    10,
    10,
    10,
    10,
    10,
    10,
    10,
    10,
    16,
    10,
    10,
    10,
    10,
    10,
    10,
    10,
    10,
    10,
    10,
    10,
    10,
    10,
    10,
    10,
    10,
    10,
    10,
    10,
    10,
    10,
    10,
    10,
    10,
    10,
    10,
    10,
    -1,
    -1,
    -1,
    -1,
    -1,
    -1,
    -1,
    -1,
    38,
    38,
    -1,
    38,
    38,
    38,
    -1,
    38,
    38,
    -1,
    38,
    -1,
    38,
    2,
    38,
    38,
    38,
    38,
    42,
    -1,
    2,
    -1,
    -1,
    32,
    16,
    22,
    -1,
    2,
    -1,
    32,
    32,
    -1,
    32,
    -1,
    32,
    44,
    32,
    44,
    32,
    -1,
    32,
    -1,
    32,
    2,
    32,
    2,
    32,
    2,
    32,
    32,
    2,
    32,
    32,
    -1,
    16,
    11,
    16,
    2,
    16,
    16,
    2,
    11,
    16,
    16,
    2,
    11,
    2,
    16,
    2,
    16,
    16,
    11,
    2,
    16,
    16,
    2,
    11,
    16,
    -1,
    16,
    16,
    2,
    11,
    16,
    2,
    16,
    2,
    11,
    11,
    2,
    16,
    16,
    -1,
    11,
    11,
    2,
    16,
    11,
    -1,
    11,
    -1,
    11,
    16,
    11,
    11,
    11,
    2,
    11,
    -1,
    11,
    -1,
    11,
    2,
    11,
    2,
    -1,
    2,
    2,
    -1,
    11,
    2,
    -1,
    2,
    2,
    11,
    21,
    11,
    2,
    -1,
    2,
    16,
    11,
    -1,
    11,
    -1,
    -1,
    2,
    2,
    21,
    21,
    2,
    -1,
    2,
    2,
    -1,
    32,
    44,
    -1,
    44,
    -1,
    -1,
    2,
    44,
    27,
    27,
    27,
    27,
    27,
    27,
    2,
    27,
    2,
    27,
    27,
    27,
    27,
    27,
    -1,
    27,
    21,
    21,
    27,
    -1,
    -1,
    2,
    -1,
    -1,
    -1,
    11,
    44,
    -1,
    -1,
    -1,
    -1,
    21,
    2,
    2,
    2,
    2,
    -1,
    2,
    2,
    2,
    -1,
    2,
    2,
    42,
    2,
    21,
    2,
    2,
    -1,
    2,
    -1,
    2,
    2,
    -1,
    -1,
    32,
    -1,
    2,
    -1,
    2,
    2,
    51,
    -1,
    -1,
    2,
    2,
    -1,
    2,
    -1,
    21,
    21,
    21,
    -1,
    21,
    -1,
    21,
    -1,
    21,
    -1,
    21,
    21,
    21,
    21,
    21,
    -1,
    21,
    21,
    42,
    21,
    21,
    2,
    21,
    21,
    2,
    21,
    2,
    2,
    44,
    2,
    -1,
    -1,
    -1,
    11,
    2,
    2,
    2,
    -1,
    2,
    16,
    2,
    -1,
    -1,
    2,
    -1,
    11,
    2,
    2,
    2,
    -1,
    2,
    -1,
    2,
    -1,
    2,
    -1,
    2,
    -1,
    2,
    -1,
    2,
    -1,
    19,
    19,
    19,
    -1,
    19,
    42,
    19,
    -1,
    19,
    19,
    19,
    -1,
    19,
    2,
    19,
    2,
    19,
    2,
    19,
    -1,
    19,
    -1,
    19,
    19,
    2,
    19,
    61,
    19,
    -1,
    19,
    -1,
    19,
    19,
    2,
    -1,
    -1,
    19,
    8,
    19,
    19,
    19,
    -1,
    2,
    21,
    -1,
    -1,
    21,
    -1,
    8,
    -1,
    2,
    19,
    2,
    19,
    -1,
    2,
    11,
    2,
    2,
    -1,
    -1,
    -1,
    27,
    2,
    -1,
    11,
    -1,
    -1,
    44,
    2,
    44,
    -1,
    11,
    -1,
    27,
    -1,
    -1,
    -1,
    2,
    8,
    8,
    42,
    8,
    8,
    -1,
    8,
    8,
    8,
    2,
    8,
    -1,
    8,
    -1,
    8,
    -1,
    8,
    -1,
    8,
    8,
    8,
    8,
    8,
    42,
    8,
    8,
    2,
    61,
    8,
    -1,
    8,
    -1,
    -1,
    8,
    18,
    -1,
    -1,
    18,
    18,
    -1,
    18,
    18,
    42,
    18,
    18,
    -1,
    18,
    42,
    18,
    18,
    -1,
    2,
    18,
    18,
    13,
    -1,
    18,
    2,
    -1,
    18,
    -1,
    2,
    18,
    -1,
    42,
    18,
    -1,
    18,
    -1,
    34,
    18,
    18,
    -1,
    18,
    -1,
    18,
    -1,
    18,
    -1,
    18,
    42,
    18,
    18,
    18,
    -1,
    18,
    -1,
    18,
    -1,
    18,
    18,
    0,
    8,
    8,
    8,
    2,
    8,
    -1,
    8,
    61,
    8,
    61,
    8,
    44,
    8,
    8,
    34,
    8,
    42,
    8,
    8,
    8,
    8,
    8,
    8,
    8,
    -1,
    8,
    8,
    8,
    8,
    -1,
    8,
    8,
    8,
    8,
    -1,
    8,
    -1,
    -1,
    8,
    -1,
    8,
    42,
    8,
    8,
    34,
    -1,
    34,
    -1,
    34,
    -1,
    34,
    34,
    -1,
    34,
    34,
    2,
    18,
    -1,
    34,
    2,
    34,
    -1,
    34,
    2,
    34,
    -1,
    34,
    34,
    34,
    2,
    34,
    34,
    34,
    42,
    -1,
    9,
    -1,
    0,
    0,
    43,
    3,
    -1,
    -1,
    26,
    26,
    26,
    26,
    26,
    26,
    26,
    26,
    26,
    48,
    48,
    48,
    48,
    26,
    26,
    17,
    48,
    48,
    26,
    26,
    26,
    26,
    26,
    26,
    26,
    26,
    26,
    48,
    26,
    26,
    26,
    48,
    48,
    48,
    48,
    48,
    0,
    -1,
    0,
    -1,
    0,
    43,
    3,
    2,
    0,
    0,
    0,
    -1,
    0,
    0,
    -1,
    35,
    35,
    35,
    35,
    13,
    35,
    35,
    35,
    0,
    35,
    35,
    35,
    35,
    35,
    35,
    35,
    35,
    35,
    0,
    35,
    35,
    0,
    -1,
    -1,
    60,
    3,
    0,
    -1,
    -1,
    53,
    -1,
    3,
    -1,
    0,
    53,
    -1,
    -1,
    -1,
    3,
    -1,
    0,
    -1,
    2,
    -1,
    -1,
    -1,
    -1,
    53,
    53,
    -1,
    3,
    -1,
    -1,
    -1,
    3,
    3,
    3,
    0,
    -1,
    3,
    0,
    0,
    3,
    -1,
    0,
    -1,
    -1,
    19,
    -1,
    -1,
    15,
    -1,
    0,
    0,
    0,
    29,
    0,
    -1,
    -1,
    7,
    -1,
    -1,
    3,
    -1,
    -1,
    -1,
    -1,
    -1,
    -1,
    0,
    -1,
    -1,
    0,
    43,
    -1,
    -1,
    13,
    13,
    -1,
    0,
    3,
    -1,
    5,
    -1,
    -1,
    -1,
    0,
    -1,
    -1,
    40,
    -1,
    -1,
    -1,
    7,
    -1,
    -1,
    -1,
    -1,
    -1,
    0,
    42,
    55,
    -1,
    52,
    7,
    -1,
    -1,
    7,
    5,
    -1,
    -1,
    -1,
    2,
    -1,
    12,
    50,
    5,
    -1,
    31,
    -1,
    20,
    -1,
    29,
    -1,
    -1,
    -1,
    -1,
    -1,
    0,
    -1,
    0,
    -1,
    -1,
    24,
    -1,
    0,
    52,
    -1,
    3,
    -1,
    50,
    -1,
    1,
    -1,
    24,
    7,
    58,
    -1,
    -1,
    -1,
    0,
    -1,
    -1,
    3,
    3,
    -1,
    -1,
    3,
    -1,
    -1,
    -1,
    -1,
    53,
    52,
    -1,
    -1,
    1,
    -1,
    -1,
    0,
    0,
    33,
    33,
    -1,
    -1,
    -1,
    -1,
    -1,
    -1,
    -1,
    -1,
    -1,
    -1,
    -1,
    5,
    2,
    0,
    -1,
    0,
    -1,
    -1,
    -1,
    -1,
    0,
    -1,
    -1,
    -1,
    0,
    -1,
    -1,
    -1,
    0,
    0,
    -1,
    -1,
    0,
    -1,
    -1,
    0,
    3,
    -1,
    -1,
    7,
    -1,
    -1,
    -1,
    -1,
    -1,
    -1,
    -1,
    -1,
    -1,
    0,
    -1,
    55,
    -1,
    -1,
    -1,
    -1,
    -1,
    40,
    9,
    53,
    -1,
    -1,
    -1,
    -1,
    2,
    -1,
    -1,
    -1,
    -1,
    -1,
    0,
    -1,
    5,
    -1,
    15,
    0,
    -1,
    3,
    24,
    -1,
    -1,
    0,
    12,
    -1,
    31,
    -1,
    -1,
    0,
    -1,
    -1,
    0,
    -1,
    -1,
    -1,
    -1,
    -1,
    -1,
    7,
    5,
    3,
    -1,
    -1,
    5,
    55,
    -1,
    3,
    -1,
    0,
    -1,
    0,
    -1,
    -1,
    1,
    1,
    -1,
    0,
    1,
    1,
    -1,
    -1,
    -1,
    -1,
    1,
    -1,
    -1,
    -1,
    1,
    1,
    1,
    -1,
    -1,
    1,
    11,
    1,
    1,
    1,
    60,
    13,
    1,
    33,
    1,
    1,
    1,
    1,
    1,
    1,
    1,
    -1,
    -1,
    1,
    1,
    1,
    1,
    1,
    1,
    1,
    -1,
    1,
    1,
    1,
    -1,
    1,
    16,
    1,
    1,
    -1,
    -1,
    1,
    1,
    13,
    -1,
    1,
    1,
    1,
    -1,
    1,
    1,
    1,
    -1,
    1,
    1,
    -1,
    -1,
    1,
    1,
    1,
    1,
    1,
    1,
    1,
    1,
    1,
    1,
    1,
    1,
    1,
    -1,
    1,
    1,
    1,
    -1,
    1,
    16,
    -1,
    -1,
    1,
    1,
    1,
    1,
    1,
    -1,
    1,
    1,
    1,
    1,
    1,
    1,
    1,
    1,
    1,
    -1,
    1,
    -1,
    1,
    1,
    -1,
    1,
    1,
    27,
    1,
    1,
    1,
    -1,
    1,
    16,
    1,
    1,
    1,
    1,
    1,
    1,
    1,
    1,
    1,
    1,
    1,
    -1,
    1,
    1,
    -1,
    1,
    1,
    1,
    1,
    40,
    1,
    1,
    -1,
    1,
    -1,
    1,
    -1,
    1,
    1,
    1,
    1,
    13,
    -1,
    -1,
    5,
    1,
    1,
    1,
    1,
    1,
    1,
    1,
    1,
    1,
    1,
    -1,
    1,
    1,
    11,
    13,
    13,
    -1,
    3,
    -1,
    -1,
    -1,
    -1,
    -1,
    0,
    -1,
    0,
    0,
    0,
    0,
    -1,
    0,
    0,
    0,
    0,
    0,
    0,
    0,
    0,
    0,
    0,
    -1,
    0,
    0,
    -1,
    -1,
    -1,
    -1,
    -1,
    0,
    -1,
    -1,
    -1,
    -1,
    0,
    0,
    0,
    27,
    -1,
    -1,
    -1,
    -1,
    -1,
    -1,
    -1,
    -1,
    7,
    -1,
    -1,
    -1,
    17,
    0,
    5,
    5,
    5,
    -1,
    -1,
    -1,
    -1,
    -1,
    -1,
    -1,
    -1,
    -1,
    0,
    0,
    0,
    45,
    17,
    0,
    -1,
    -1,
    -1,
    -1,
    -1,
    -1,
    -1,
    -1,
    -1,
    0,
    -1,
    0,
    0,
    -1,
    -1,
    0,
    0,
    7,
    -1,
    -1,
    -1,
    9,
    -1,
    -1,
    -1,
    -1,
    -1,
    3,
    -1,
    -1,
    7,
    -1,
    -1,
    -1,
    -1,
    -1,
    31,
    -1,
    -1,
    -1,
    -1,
    27,
    -1,
    3,
    -1,
    -1,
    -1,
    0,
    -1,
    40,
    5,
    50,
    -1,
    0,
    -1,
    9,
    -1,
    24,
    24,
    33,
    33,
    -1,
    -1,
    -1,
    -1,
    5,
    15,
    15,
    15,
    15,
    -1,
    52,
    -1,
    -1,
    -1,
    -1,
    5,
    31,
    -1,
    -1,
    58,
    13,
    -1,
    13,
    3,
    -1,
    -1,
    -1,
    -1,
    12,
    13,
    13,
    -1,
    -1,
    -1,
    -1,
    43,
    -1,
    0,
    59,
    -1,
    -1,
    -1,
    0,
    0,
    -1,
    -1,
    0,
    -1,
    -1,
    -1,
    57,
    -1,
    -1,
    -1,
    -1,
    -1,
    0,
    0,
    -1,
    -1,
    -1,
    7,
    -1,
    -1,
    -1,
    0,
    -1,
    -1,
    0,
    -1,
    0,
    -1,
    -1,
    -1,
    0,
    0,
    0,
    -1,
    3,
    -1,
    -1,
    -1,
    -1,
    0,
    -1,
    -1,
    -1,
    -1,
    -1,
    3,
    3,
    -1,
    -1,
    -1,
    9,
    -1,
    -1,
    -1,
    1,
    -1,
    -1,
    -1,
    -1,
    -1,
    -1,
    -1,
    -1,
    -1,
    3,
    -1,
    -1,
    5,
    -1,
    -1,
    -1,
    3,
    0,
    -1,
    40,
    0,
    -1,
    -1,
    7,
    50,
    -1,
    -1,
    7,
    5,
    -1,
    -1,
    -1,
    -1,
    -1,
    20,
    0,
    0,
    0,
    -1,
    0,
    33,
    -1,
    -1,
    5,
    15,
    -1,
    -1,
    -1,
    7,
    7,
    -1,
    50,
    -1,
    -1,
    0,
    -1,
    -1,
    5,
    57,
    57,
    -1,
    59,
    -1,
    -1,
    -1,
    -1,
    7,
    -1,
    0,
    0,
    -1,
    -1,
    -1,
    -1,
    -1,
    0,
    -1,
    -1,
    3,
    -1,
    -1,
    5,
    -1,
    -1,
    -1,
    -1,
    -1,
    -1,
    5,
    -1,
    5,
    -1,
    -1,
    -1,
    -1,
    55,
    55,
    55,
    55,
    -1,
    -1,
    12,
    -1,
    -1,
    12,
    -1,
    56,
    3,
    -1,
    0,
    0,
    0,
    -1,
    0,
    0,
    0,
    -1,
    0,
    0,
    -1,
    9,
    -1,
    0,
    -1,
    -1,
    5,
    0,
    -1,
    13,
    12,
    -1,
    15,
    -1,
    46,
    3,
    0,
    -1,
    0,
    0,
    0,
    -1,
    -1,
    0,
    -1,
    -1,
    -1,
    -1,
    -1,
    -1,
    -1,
    13,
    -1,
    -1,
    -1,
    -1,
    -1,
    -1,
    7,
    -1,
    -1,
    -1,
    -1,
    -1,
    1,
    43,
    -1,
    50,
    9,
    -1,
    -1,
    9,
    0,
    -1,
    33,
    -1,
    -1,
    -1,
    33,
    -1,
    5,
    0,
    16,
    0,
    -1,
    -1,
    -1,
    -1,
    60,
    60,
    55,
    -1,
    0,
    0,
    -1,
    -1,
    -1,
    -1,
    -1,
    -1,
    -1,
    3,
    0,
    33,
    -1,
    0,
    2,
    51,
    -1,
    -1,
    -1,
    0,
    0,
    0,
    0,
    3,
    -1,
    45,
    0,
    0,
    0,
    -1,
    -1,
    -1,
    -1,
    41,
    -1,
    3,
    13,
    12,
    -1,
    -1,
    -1,
    -1,
    -1,
    5,
    5,
    -1,
    0,
    0,
    0,
    0,
    0,
    -1,
    -1,
    29,
    9,
    -1,
    0,
    -1,
    58,
    -1,
    5,
    -1,
    7,
    -1,
    -1,
    -1,
    -1,
    2,
    -1,
    0,
    2,
    15,
    15,
    15,
    17,
    -1,
    0,
    0,
    9,
    5,
    -1,
    -1,
    5,
    30,
    -1,
    -1,
    -1,
    0,
    0,
    -1,
    -1,
    43,
    -1,
    57,
    -1,
    9,
    9,
    -1,
    9,
    9,
    9,
    3,
    -1,
    45,
    -1,
    45,
    -1,
    -1,
    43,
    -1,
    -1,
    -1,
    -1,
    2,
    2,
    5,
    43,
    -1,
    0,
    9,
    -1,
    3,
    5,
    -1,
    3
  ],
  "topic_sizes": {
    "0": 756,
    "-1": 1888,
    "3": 109,
    "15": 34,
    "7": 54,
    "5": 81,
    "12": 36,
    "29": 21,
    "50": 12,
    "9": 52,
    "24": 23,
    "1": 141,
    "19": 31,
    "4": 83,
    "23": 24,
    "44": 13,
    "21": 28,
    "38": 16,
    "61": 5,
    "51": 12,
    "25": 23,
    "2": 135,
    "6": 80,
    "43": 13,
    "59": 6,
    "45": 13,
    "56": 7,
    "52": 11,
    "33": 19,
    "53": 11,
    "20": 29,
    "32": 20,
    "13": 35,
    "30": 21,
    "11": 37,
    "55": 10,
    "14": 35,
    "60": 6,
    "57": 7,
    "58": 6,
    "27": 22,
    "22": 25,
    "16": 32,
    "37": 17,
    "31": 20,
    "40": 14,
    "17": 32,
    "49": 12,
    "47": 13,
    "36": 18,
    "54": 11,
    "46": 13,
    "39": 15,
    "28": 21,
    "41": 14,
    "10": 44,
    "42": 14,
    "8": 53,
    "18": 31,
    "34": 19,
    "26": 23,
    "48": 12,
    "35": 18
  },
  "topic_mapper": [
    [
      -1,
      -1,
      -1
    ],
    [
      0,
      0,
      14
    ],
    [
      1,
      1,
      6
    ],
    [
      2,
      2,
      23
    ],
    [
      3,
      3,
      40
    ],
    [
      4,
      4,
      10
    ],
    [
      5,
      5,
      53
    ],
    [
      6,
      6,
      58
    ],
    [
      7,
      7,
      27
    ],
    [
      8,
      8,
      13
    ],
    [
      9,
      9,
      1
    ],
    [
      10,
      10,
      9
    ],
    [
      11,
      11,
      45
    ],
    [
      12,
      12,
      50
    ],
    [
      13,
      13,
      59
    ],
    [
      14,
      14,
      36
    ],
    [
      15,
      15,
      18
    ],
    [
      16,
      16,
      29
    ],
    [
      17,
      17,
      52
    ],
    [
      18,
      18,
      28
    ],
    [
      19,
      19,
      8
    ],
    [
      20,
      20,
      33
    ],
    [
      21,
      21,
      3
    ],
    [
      22,
      22,
      7
    ],
    [
      23,
      23,
      34
    ],
    [
      24,
      24,
      31
    ],
    [
      25,
      25,
      0
    ],
    [
      26,
      26,
      48
    ],
    [
      27,
      27,
      12
    ],
    [
      28,
      28,
      55
    ],
    [
      29,
      29,
      11
    ],
    [
      30,
      30,
      38
    ],
    [
      31,
      31,
      32
    ],
    [
      32,
      32,
      39
    ],
    [
      33,
      33,
      43
    ],
    [
      34,
      34,
      24
    ],
    [
      35,
      35,
      30
    ],
    [
      36,
      36,
      56
    ],
    [
      37,
      37,
      57
    ],
    [
      38,
      38,
      35
    ],
    [
      39,
      39,
      5
    ],
    [
      40,
      40,
      60
    ],
    [
      41,
      41,
      15
    ],
    [
      42,
      42,
      19
    ],
    [
      43,
      43,
      20
    ],
    [
      44,
      44,
      44
    ],
    [
      45,
      45,
      21
    ],
    [
      46,
      46,
      2
    ],
    [
      47,
      47,
      16
    ],
    [
      48,
      48,
      26
    ],
    [
      49,
      49,
      51
    ],
    [
      50,
      50,
      4
    ],
    [
      51,
      51,
      25
    ],
    [
      52,
      52,
      42
    ],
    [
      53,
      53,
      61
    ],
    [
      54,
      54,
      37
    ],
    [
      55,
      55,
      22
    ],
    [
      56,
      56,
      17
    ],
    [
      57,
      57,
      46
    ],
    [
      58,
      58,
      49
    ],
    [
      59,
      59,
      41
    ],
    [
      60,
      60,
      47
    ],
    [
      61,
      61,
      54
    ]
  ],
  "topic_labels": {
    "-1": "-1_und_der_die_in",
    "0": "0_vnd_da_und_der",
    "1": "1_die_sie_und_der",
    "2": "2_die_der_und_zu",
    "3": "3_und_ein_sie_es",
    "4": "4_der_die_des_und",
    "5": "5_ich_er_und_sie",
    "6": "6_die_der_des_den",
    "7": "7_und_die_der_in",
    "8": "8_die_der_den_und",
    "9": "9_und_die_der_in",
    "10": "10_marburger_marburg_der_die",
    "11": "11_die_der_und_des",
    "12": "12_die_der_und_den",
    "13": "13_die_der_und_in",
    "14": "14_in_die_der_fuer",
    "15": "15_die_der_man_ist",
    "16": "16_juli_der_die_und",
    "17": "17_der_die_in_und",
    "18": "18_die_der_maerz_zu",
    "19": "19_die_vnd_der_in",
    "20": "20_der_die_des_von",
    "21": "21_nationalversammlung_die_der_zu",
    "22": "22_von_und_der_den",
    "23": "23_der_die_in_des",
    "24": "24_und_der_die_er",
    "25": "25_von_der_und_den",
    "26": "26_fl_der_die_wien",
    "27": "27_die_der_in_und",
    "28": "28_czernowitz_cz_der_die",
    "29": "29_du_und_ich_die",
    "30": "30_der_die_und_in",
    "31": "31_der_des_die_von",
    "32": "32_die_juni_der_zu",
    "33": "33_sie_ich_er_und",
    "34": "34_mai_die_der_und",
    "35": "35_fr_der_die_rp",
    "36": "36_auswanderer_und_die_fuer",
    "37": "37_jhro_von_majest_affairen",
    "38": "38_die_der_juni_und",
    "39": "39_czernowitz_der_die_in",
    "40": "40_nr_ich_vgl_bayreuth",
    "41": "41_der_des_die_in",
    "42": "42_die_sgr_koeln_der",
    "43": "43_frauen_frauenstimmrecht_frau_die",
    "44": "44_die_der_in_den",
    "45": "45_und_frag_da_so",
    "46": "46_und_auch_in_oder",
    "47": "47_exped_offerten_fuer_bef",
    "48": "48_der_dr_wien_die",
    "49": "49_ich_er_und_zu",
    "50": "50_ich_sie_und_nicht",
    "51": "51_die_der_zu_von",
    "52": "52_die_und_der_den",
    "53": "53_der_die_und_von",
    "54": "54_und_auswanderer_cpt_von",
    "55": "55_der_die_den_er",
    "56": "56_tab_rc_bey_fr",
    "57": "57_die_der_ist_eine",
    "58": "58_die_der_und_ist",
    "59": "59_und_der_die_zu",
    "60": "60_ii_lat_holl_harrebomee",
    "61": "61_der_die_und_des"
  },
  "custom_labels": null,
  "_outliers": 1,
  "topic_aspects": {}
}